[
  {
    "title": "Intégrateur Web",
    "subtitle": "Intégrateur Web",
    "duration": "2024-2025",
    "description": "Formation Intégrateur web OpenClassroom"
  },
  {
    "title": "Agent desecurité incendie",
    "subtitle": "SSIAP1",
    "duration": "2016-2022",
    "description": "centre de formation incendie cfps Lyon"
  },
  {
    "title": "Divers mission interim ",
    "subtitle": "Batiments",
    "duration": "2009-2016",
    "description": "Traveaux Batiments"
  },
  {
    "title": "Frigoriste",
    "subtitle": "Réparation d'équipements frigorifiques",
    "duration": "2001-2009",
    "description": "Réalisation, maintenance chambres Froides "
  }
]
