{
  "frontend": [
    { "label": "HTML", "icon": "bx bxl-html5", "colorClass": "html-color" },
    { "label": "Sass", "icon": "bx bxl-sass", "colorClass": "sass-color" },
    {
      "label": "JavaScript",
      "icon": "bx bxl-javascript",
      "colorClass": "javascript-color"
    },
    { "label": "React", "icon": "bx bxl-react", "colorClass": "react-color" },
    { "label": "Figma", "icon": "bx bxl-figma", "colorClass": "figma-color" }
  ],
  "backend": [
    {
      "label": "MongoDB",
      "icon": "bx bxl-mongodb",
      "colorClass": "mongodb-color"
    },
    { "label": "Redux", "icon": "bx bxl-redux", "colorClass": "redux-color" },
    {
      "label": "GitHub",
      "icon": "bx bxl-github",
      "colorClass": "github-color"
    },
    { "label": "CSS", "icon": "bx bxl-css3", "colorClass": "css-color" }
  ]
}
